{"충북__5__증평군나선거구":{"선거인수":0,"투표수":0,"무효":0,"기권":0,"무투표":true,"candidates":[]},"충북__5__증평군다선거구":{"선거인수":0,"투표수":0,"무효":0,"기권":0,"무투표":true,"candidates":[]},"충북__5__증평군가선거구":{"선거인수":0,"투표수":0,"무효":0,"기권":0,"무투표":true,"candidates":[]},"충북__5__청주시제1선거구":{"선거인수":0,"투표수":0,"무효":0,"기권":0,"무투표":true,"candidates":[]},"충북__5__청주시제2선거구":{"선거인수":0,"투표수":0,"무효":0,"기권":0,"무투표":true,"candidates":[]},"충북__5__청주시제3선거구":{"선거인수":0,"투표수":0,"무효":0,"기권":0,"무투표":true,"candidates":[]},"충북__5__청주시라선거구":{"선거인수":0,"투표수":0,"무효":0,"기권":0,"무투표":true,"candidates":[]},"충북__5__청주시마선거구":{"선거인수":0,"투표수":0,"무효":0,"기권":0,"무투표":true,"candidates":[]},"충북__6__증평군가선거구":{"선거인수":0,"투표수":0,"무효":0,"기권":0,"무투표":true,"candidates":[]},"충북__5__청주시바선거구":{"선거인수":0,"투표수":0,"무효":0,"기권":0,"무투표":true,"candidates":[]},"충북__6__증평군나선거구":{"선거인수":0,"투표수":0,"무효":0,"기권":0,"무투표":true,"candidates":[]},"충북__6__증평군다선거구":{"선거인수":0,"투표수":0,"무효":0,"기권":0,"무투표":true,"candidates":[]},"충북__5__청주시사선거구":{"선거인수":76314,"투표수":42933,"무효":1967,"기권":33381,"candidates":[{"label":"더불어민주당김은교","votes":13335},{"label":"더불어민주당김병년","votes":5633},{"label":"더불어민주당최동식","votes":5997},{"label":"국민의힘김종식","votes":9593},{"label":"국민의힘박노학","votes":6408}]},"충북__5__청주시아선거구":{"선거인수":0,"투표수":0,"무효":0,"기권":0,"무투표":true,"candidates":[]},"충북__5__청주시자선거구":{"선거인수":0,"투표수":0,"무효":0,"기권":0,"무투표":true,"candidates":[]},"충북__5__청주시차선거구":{"선거인수":0,"투표수":0,"무효":0,"기권":0,"무투표":true,"candidates":[]},"충남__5__천안시제4선거구":{"선거인수":0,"투표수":0,"무효":0,"기권":0,"무투표":true,"candidates":[]},"충북__5__천안시제4선거구":{"선거인수":52990,"투표수":31201,"무효":470,"기권":21789,"candidates":[{"label":"더불어민주당구형서","votes":20145},{"label":"국민의힘김은주","votes":10586}]},"충북__5__천안시제5선거구":{"선거인수":62727,"투표수":32591,"무효":660,"기권":30136,"candidates":[{"label":"더불어민주당김재호","votes":16465},{"label":"국민의힘유성재","votes":15466}]},"충남__5__천안시제5선거구":{"선거인수":0,"투표수":0,"무효":0,"기권":0,"무투표":true,"candidates":[]},"충북__5__천안시제6선거구":{"선거인수":49471,"투표수":24734,"무효":394,"기권":24737,"candidates":[{"label":"더불어민주당김선홍","votes":14725},{"label":"국민의힘이상구","votes":9615}]},"충남__5__천안시제6선거구":{"선거인수":0,"투표수":0,"무효":0,"기권":0,"무투표":true,"candidates":[]},"충북__5__천안시제7선거구":{"선거인수":49406,"투표수":25018,"무효":339,"기권":24388,"candidates":[{"label":"더불어민주당진성범","votes":15450},{"label":"국민의힘김영경","votes":9229}]},"충남__5__천안시제7선거구":{"선거인수":0,"투표수":0,"무효":0,"기권":0,"무투표":true,"candidates":[]},"충북__5__천안시제8선거구":{"선거인수":31668,"투표수":18133,"무효":281,"기권":13535,"candidates":[{"label":"더불어민주당정병인","votes":11484},{"label":"국민의힘강문식","votes":6368}]},"충남__5__천안시제8선거구":{"선거인수":0,"투표수":0,"무효":0,"기권":0,"무투표":true,"candidates":[]},"충북__5__천안시제11선거구":{"선거인수":54972,"투표수":30502,"무효":548,"기권":24470,"candidates":[{"label":"더불어민주당김은나","votes":16384},{"label":"국민의힘이현숙","votes":13570}]},"충남__5__천안시제11선거구":{"선거인수":0,"투표수":0,"무효":0,"기권":0,"무투표":true,"candidates":[]},"충남__5__천안시제1선거구":{"선거인수":0,"투표수":0,"무효":0,"기권":0,"무투표":true,"candidates":[]},"충북__5__천안시제1선거구":{"선거인수":0,"투표수":0,"무효":0,"기권":0,"무투표":true,"candidates":[]},"충북__5__천안시제2선거구":{"선거인수":0,"투표수":0,"무효":0,"기권":0,"무투표":true,"candidates":[]},"충남__5__천안시제2선거구":{"선거인수":0,"투표수":0,"무효":0,"기권":0,"무투표":true,"candidates":[]},"충북__5__천안시제3선거구":{"선거인수":0,"투표수":0,"무효":0,"기권":0,"무투표":true,"candidates":[]},"충남__5__천안시제3선거구":{"선거인수":0,"투표수":0,"무효":0,"기권":0,"무투표":true,"candidates":[]},"충북__5__천안시제9선거구":{"선거인수":0,"투표수":0,"무효":0,"기권":0,"무투표":true,"candidates":[]},"충남__5__천안시제9선거구":{"선거인수":0,"투표수":0,"무효":0,"기권":0,"무투표":true,"candidates":[]},"충북__5__천안시제10선거구":{"선거인수":0,"투표수":0,"무효":0,"기권":0,"무투표":true,"candidates":[]},"충남__5__천안시제10선거구":{"선거인수":0,"투표수":0,"무효":0,"기권":0,"무투표":true,"candidates":[]},"충북__6__천안시제1선거구":{"선거인수":0,"투표수":0,"무효":0,"기권":0,"무투표":true,"candidates":[]},"충북__6__천안시제2선거구":{"선거인수":0,"투표수":0,"무효":0,"기권":0,"무투표":true,"candidates":[]},"충북__6__천안시제3선거구":{"선거인수":0,"투표수":0,"무효":0,"기권":0,"무투표":true,"candidates":[]},"충북__6__천안시제9선거구":{"선거인수":0,"투표수":0,"무효":0,"기권":0,"무투표":true,"candidates":[]},"충북__5__단양군가선거구":{"선거인수":0,"투표수":0,"무효":0,"기권":0,"무투표":true,"candidates":[]},"충북__6__천안시제10선거구":{"선거인수":0,"투표수":0,"무효":0,"기권":0,"무투표":true,"candidates":[]},"충북__5__단양군나선거구":{"선거인수":0,"투표수":0,"무효":0,"기권":0,"무투표":true,"candidates":[]},"충북__5__공주시제1선거구":{"선거인수":0,"투표수":0,"무효":0,"기권":0,"무투표":true,"candidates":[]},"충북__5__공주시제2선거구":{"선거인수":0,"투표수":0,"무효":0,"기권":0,"무투표":true,"candidates":[]},"충남__5__보령시제1선거구":{"선거인수":0,"투표수":0,"무효":0,"기권":0,"무투표":true,"candidates":[]},"충남__5__보령시제2선거구":{"선거인수":0,"투표수":0,"무효":0,"기권":0,"무투표":true,"candidates":[]},"충북__5__아산시제1선거구":{"선거인수":0,"투표수":0,"무효":0,"기권":0,"무투표":true,"candidates":[]},"충북__5__아산시제2선거구":{"선거인수":0,"투표수":0,"무효":0,"기권":0,"무투표":true,"candidates":[]},"충남__5__아산시제1선거구":{"선거인수":0,"투표수":0,"무효":0,"기권":0,"무투표":true,"candidates":[]},"충북__5__아산시제3선거구":{"선거인수":0,"투표수":0,"무효":0,"기권":0,"무투표":true,"candidates":[]},"충남__5__아산시제2선거구":{"선거인수":0,"투표수":0,"무효":0,"기권":0,"무투표":true,"candidates":[]},"충북__5__아산시제4선거구":{"선거인수":0,"투표수":0,"무효":0,"기권":0,"무투표":true,"candidates":[]},"충남__5__아산시제3선거구":{"선거인수":0,"투표수":0,"무효":0,"기권":0,"무투표":true,"candidates":[]},"충북__5__아산시제5선거구":{"선거인수":0,"투표수":0,"무효":0,"기권":0,"무투표":true,"candidates":[]},"충남__5__아산시제4선거구":{"선거인수":0,"투표수":0,"무효":0,"기권":0,"무투표":true,"candidates":[]},"충북__5__아산시제6선거구":{"선거인수":0,"투표수":0,"무효":0,"기권":0,"무투표":true,"candidates":[]},"충남__5__아산시제5선거구":{"선거인수":0,"투표수":0,"무효":0,"기권":0,"무투표":true,"candidates":[]},"충남__5__아산시제6선거구":{"선거인수":0,"투표수":0,"무효":0,"기권":0,"무투표":true,"candidates":[]},"충북__6__서산시제1선거구":{"선거인수":0,"투표수":0,"무효":0,"기권":0,"무투표":true,"candidates":[]},"충북__6__서산시제2선거구":{"선거인수":0,"투표수":0,"무효":0,"기권":0,"무투표":true,"candidates":[]},"충북__6__서산시제3선거구":{"선거인수":0,"투표수":0,"무효":0,"기권":0,"무투표":true,"candidates":[]},"충북__5__괴산군가선거구":{"선거인수":0,"투표수":0,"무효":0,"기권":0,"무투표":true,"candidates":[]},"충북__5__괴산군나선거구":{"선거인수":0,"투표수":0,"무효":0,"기권":0,"무투표":true,"candidates":[]},"충북__5__괴산군다선거구":{"선거인수":0,"투표수":0,"무효":0,"기권":0,"무투표":true,"candidates":[]},"충남__5__서산시제1선거구":{"선거인수":0,"투표수":0,"무효":0,"기권":0,"무투표":true,"candidates":[]},"충북__5__서산시제1선거구":{"선거인수":0,"투표수":0,"무효":0,"기권":0,"무투표":true,"candidates":[]},"충북__5__서산시제2선거구":{"선거인수":0,"투표수":0,"무효":0,"기권":0,"무투표":true,"candidates":[]},"충남__5__서산시제2선거구":{"선거인수":0,"투표수":0,"무효":0,"기권":0,"무투표":true,"candidates":[]},"충북__5__서산시제3선거구":{"선거인수":0,"투표수":0,"무효":0,"기권":0,"무투표":true,"candidates":[]},"충남__5__서산시제3선거구":{"선거인수":0,"투표수":0,"무효":0,"기권":0,"무투표":true,"candidates":[]},"충남__5__태안군제1선거구":{"선거인수":0,"투표수":0,"무효":0,"기권":0,"무투표":true,"candidates":[]},"충남__5__태안군제2선거구":{"선거인수":0,"투표수":0,"무효":0,"기권":0,"무투표":true,"candidates":[]},"충남__5__공주시제1선거구":{"선거인수":0,"투표수":0,"무효":0,"기권":0,"무투표":true,"candidates":[]},"충남__5__공주시제2선거구":{"선거인수":0,"투표수":0,"무효":0,"기권":0,"무투표":true,"candidates":[]},"충남__5__금산군제1선거구":{"선거인수":0,"투표수":0,"무효":0,"기권":0,"무투표":true,"candidates":[]},"충남__5__금산군제2선거구":{"선거인수":0,"투표수":0,"무효":0,"기권":0,"무투표":true,"candidates":[]},"충남__5__논산시제1선거구":{"선거인수":0,"투표수":0,"무효":0,"기권":0,"무투표":true,"candidates":[]},"충남__5__논산시제2선거구":{"선거인수":0,"투표수":0,"무효":0,"기권":0,"무투표":true,"candidates":[]},"충남__5__당진시제1선거구":{"선거인수":0,"투표수":0,"무효":0,"기권":0,"무투표":true,"candidates":[]},"충남__5__당진시제2선거구":{"선거인수":0,"투표수":0,"무효":0,"기권":0,"무투표":true,"candidates":[]},"충남__5__당진시제3선거구":{"선거인수":0,"투표수":0,"무효":0,"기권":0,"무투표":true,"candidates":[]},"충남__5__부여군제1선거구":{"선거인수":25518,"투표수":18089,"무효":450,"기권":7429,"candidates":[{"label":"더불어민주당민병희","votes":9365},{"label":"국민의힘정헌구","votes":8274}]},"충남__5__부여군제2선거구":{"선거인수":0,"투표수":0,"무효":0,"기권":0,"무투표":true,"candidates":[]},"충북__5__부여군제1선거구":{"선거인수":0,"투표수":0,"무효":0,"기권":0,"무투표":true,"candidates":[]},"충남__5__증평군선거구":{"선거인수":0,"투표수":0,"무효":0,"기권":0,"무투표":true,"candidates":[]},"충북__5__부여군제2선거구":{"선거인수":0,"투표수":0,"무효":0,"기권":0,"무투표":true,"candidates":[]},"충남__5__서천군제1선거구":{"선거인수":0,"투표수":0,"무효":0,"기권":0,"무투표":true,"candidates":[]},"충남__5__괴산군가선거구":{"선거인수":15680,"투표수":11639,"무효":681,"기권":4041,"candidates":[{"label":"더불어민주당최경섭","votes":3327},{"label":"더불어민주당이덕용","votes":2666},{"label":"국민의힘이형배","votes":2311},{"label":"국민의힘김영희","votes":1852},{"label":"무소속최관선","votes":802}]},"충남__5__서천군제2선거구":{"선거인수":0,"투표수":0,"무효":0,"기권":0,"무투표":true,"candidates":[]},"충남__5__괴산군나선거구":{"선거인수":8583,"투표수":6500,"무효":400,"기권":2083,"candidates":[{"label":"더불어민주당박천웅","votes":1998},{"label":"국민의힘김주성","votes":2126},{"label":"국민의힘송영순","votes":1274},{"label":"무소속박선옥","votes":702}]},"충남__5__괴산군다선거구":{"선거인수":8583,"투표수":6500,"무효":400,"기권":2083,"candidates":[{"label":"더불어민주당박천웅","votes":1998},{"label":"국민의힘김주성","votes":2126},{"label":"국민의힘송영순","votes":1274},{"label":"무소속박선옥","votes":702}]},"충남__5__예산군제1선거구":{"선거인수":33507,"투표수":21182,"무효":482,"기권":12325,"candidates":[{"label":"더불어민주당이용도","votes":6419},{"label":"국민의힘최광선","votes":8321},{"label":"무소속방한일","votes":5960}]},"충남__5__예산군제2선거구":{"선거인수":37539,"투표수":23545,"무효":737,"기권":13994,"candidates":[{"label":"더불어민주당김영춘","votes":9702},{"label":"국민의힘전달수","votes":13106}]},"충남__5__청양군선거구":{"선거인수":0,"투표수":0,"무효":0,"기권":0,"무투표":true,"candidates":[]},"충북__6__괴산군가선거구":{"선거인수":15680,"투표수":11639,"무효":681,"기권":4041,"candidates":[{"label":"더불어민주당최경섭","votes":3327},{"label":"더불어민주당이덕용","votes":2666},{"label":"국민의힘이형배","votes":2311},{"label":"국민의힘김영희","votes":1852},{"label":"무소속최관선","votes":802}]},"충북__6__괴산군나선거구":{"선거인수":8583,"투표수":6500,"무효":400,"기권":2083,"candidates":[{"label":"더불어민주당박천웅","votes":1998},{"label":"국민의힘김주성","votes":2126},{"label":"국민의힘송영순","votes":1274},{"label":"무소속박선옥","votes":702}]},"충북__6__괴산군다선거구":{"선거인수":0,"투표수":0,"무효":0,"기권":0,"무투표":true,"candidates":[]},"충북__6__청주시가선거구":{"선거인수":0,"투표수":0,"무효":0,"기권":0,"무투표":true,"candidates":[]},"충북__6__청주시나선거구":{"선거인수":0,"투표수":0,"무효":0,"기권":0,"무투표":true,"candidates":[]},"충북__6__청주시다선거구":{"선거인수":0,"투표수":0,"무효":0,"기권":0,"무투표":true,"candidates":[]},"충북__6__청주시라선거구":{"선거인수":0,"투표수":0,"무효":0,"기권":0,"무투표":true,"candidates":[]},"충북__6__청주시마선거구":{"선거인수":0,"투표수":0,"무효":0,"기권":0,"무투표":true,"candidates":[]},"충북__6__청주시바선거구":{"선거인수":53296,"투표수":29725,"무효":1580,"기권":23571,"candidates":[{"label":"더불어민주당신민수","votes":10646},{"label":"더불어민주당박대용","votes":4449},{"label":"국민의힘최영중","votes":5728},{"label":"국민의힘홍성각","votes":6283},{"label":"진보당이복규","votes":1039}]},"충북__6__청주시사선거구":{"선거인수":76314,"투표수":42933,"무효":1967,"기권":33381,"candidates":[{"label":"더불어민주당김은교","votes":13335},{"label":"더불어민주당김병년","votes":5633},{"label":"더불어민주당최동식","votes":5997},{"label":"국민의힘김종식","votes":9593},{"label":"국민의힘박노학","votes":6408}]},"충북__6__청주시아선거구":{"선거인수":0,"투표수":0,"무효":0,"기권":0,"무투표":true,"candidates":[]},"충북__6__청주시자선거구":{"선거인수":0,"투표수":0,"무효":0,"기권":0,"무투표":true,"candidates":[]},"충북__6__청주시차선거구":{"선거인수":0,"투표수":0,"무효":0,"기권":0,"무투표":true,"candidates":[]},"충북__6__청주시카선거구":{"선거인수":0,"투표수":0,"무효":0,"기권":0,"무투표":true,"candidates":[]},"충북__6__청주시타선거구":{"선거인수":54052,"투표수":29759,"무효":803,"기권":24293,"candidates":[{"label":"더불어민주당허희","votes":8393},{"label":"더불어민주당이예숙","votes":4407},{"label":"더불어민주당송병호","votes":5427},{"label":"국민의힘김성수","votes":8532},{"label":"무소속이상용","votes":584},{"label":"무소속상병남","votes":1613}]},"충북__6__청주시파선거구":{"선거인수":29888,"투표수":16298,"무효":403,"기권":13590,"candidates":[{"label":"더불어민주당한용진","votes":6352},{"label":"국민의힘정태훈","votes":6998},{"label":"조국혁신당임정수","votes":863},{"label":"정의당이병주","votes":191},{"label":"무소속최혜림","votes":1059},{"label":"무소속김광복","votes":432}]},"충북__6__청주시하선거구":{"선거인수":0,"투표수":0,"무효":0,"기권":0,"무투표":true,"candidates":[]},"충북__6__천안시제4선거구":{"선거인수":0,"투표수":0,"무효":0,"기권":0,"무투표":true,"candidates":[]},"충북__6__천안시제5선거구":{"선거인수":0,"투표수":0,"무효":0,"기권":0,"무투표":true,"candidates":[]},"충북__6__충주시가선거구":{"선거인수":0,"투표수":0,"무효":0,"기권":0,"무투표":true,"candidates":[]},"충북__6__천안시제6선거구":{"선거인수":0,"투표수":0,"무효":0,"기권":0,"무투표":true,"candidates":[]},"충북__6__충주시나선거구":{"선거인수":0,"투표수":0,"무효":0,"기권":0,"무투표":true,"candidates":[]},"충북__6__천안시제7선거구":{"선거인수":0,"투표수":0,"무효":0,"기권":0,"무투표":true,"candidates":[]},"충북__6__충주시다선거구":{"선거인수":0,"투표수":0,"무효":0,"기권":0,"무투표":true,"candidates":[]},"충북__6__천안시제8선거구":{"선거인수":0,"투표수":0,"무효":0,"기권":0,"무투표":true,"candidates":[]},"충북__6__충주시라선거구":{"선거인수":54065,"투표수":31920,"무효":1785,"기권":22145,"candidates":[{"label":"더불어민주당유영기","votes":10213},{"label":"더불어민주당장준기","votes":3790},{"label":"국민의힘고민서","votes":7486},{"label":"국민의힘서원복","votes":4350},{"label":"국민의힘권설규","votes":1557},{"label":"무소속민병윤","votes":2739}]},"충북__6__천안시제11선거구":{"선거인수":0,"투표수":0,"무효":0,"기권":0,"무투표":true,"candidates":[]},"충북__6__충주시마선거구":{"선거인수":13079,"투표수":8477,"무효":439,"기권":4602,"candidates":[{"label":"더불어민주당손상현","votes":3109},{"label":"국민의힘심재익","votes":3337},{"label":"국민의힘강명철","votes":1592}]},"충북__6__충주시바선거구":{"선거인수":0,"투표수":0,"무효":0,"기권":0,"무투표":true,"candidates":[]},"충북__6__충주시사선거구":{"선거인수":0,"투표수":0,"무효":0,"기권":0,"무투표":true,"candidates":[]},"충북__6__제천시가선거구":{"선거인수":0,"투표수":0,"무효":0,"기권":0,"무투표":true,"candidates":[]},"충북__6__제천시나선거구":{"선거인수":0,"투표수":0,"무효":0,"기권":0,"무투표":true,"candidates":[]},"충북__6__제천시다선거구":{"선거인수":0,"투표수":0,"무효":0,"기권":0,"무투표":true,"candidates":[]},"충북__6__제천시라선거구":{"선거인수":0,"투표수":0,"무효":0,"기권":0,"무투표":true,"candidates":[]},"충북__6__제천시마선거구":{"선거인수":0,"투표수":0,"무효":0,"기권":0,"무투표":true,"candidates":[]},"충북__6__제천시바선거구":{"선거인수":0,"투표수":0,"무효":0,"기권":0,"무투표":true,"candidates":[]},"충북__6__단양군가선거구":{"선거인수":0,"투표수":0,"무효":0,"기권":0,"무투표":true,"candidates":[]},"충북__6__단양군나선거구":{"선거인수":0,"투표수":0,"무효":0,"기권":0,"무투표":true,"candidates":[]},"충북__6__영동군가선거구":{"선거인수":0,"투표수":0,"무효":0,"기권":0,"무투표":true,"candidates":[]},"충북__6__영동군나선거구":{"선거인수":0,"투표수":0,"무효":0,"기권":0,"무투표":true,"candidates":[]},"충북__6__영동군다선거구":{"선거인수":9314,"투표수":6771,"무효":218,"기권":2543,"candidates":[{"label":"더불어민주당손석구","votes":2044},{"label":"국민의힘김오봉","votes":2425},{"label":"국민의힘박용성","votes":2084}]},"충남__6__천안시제4선거구":{"선거인수":0,"투표수":0,"무효":0,"기권":0,"무투표":true,"candidates":[]},"충남__6__천안시제5선거구":{"선거인수":0,"투표수":0,"무효":0,"기권":0,"무투표":true,"candidates":[]},"충북__6__천안시라선거구":{"선거인수":52990,"투표수":31201,"무효":604,"기권":21789,"candidates":[{"label":"더불어민주당김세환","votes":8752},{"label":"더불어민주당최혜선","votes":4394},{"label":"국민의힘이교희","votes":7867},{"label":"조국혁신당이나현","votes":1267},{"label":"개혁신당이강민","votes":708},{"label":"무소속이종담","votes":3124},{"label":"무소속장혁","votes":4485}]},"충북__6__천안시마선거구":{"선거인수":43953,"투표수":22960,"무효":1743,"기권":20993,"candidates":[{"label":"더불어민주당윤철상","votes":7693},{"label":"더불어민주당육종영","votes":3854},{"label":"국민의힘엄기환","votes":4406},{"label":"국민의힘김철환","votes":5264}]},"충남__6__천안시제6선거구":{"선거인수":0,"투표수":0,"무효":0,"기권":0,"무투표":true,"candidates":[]},"충북__6__천안시바선거구":{"선거인수":68245,"투표수":34367,"무효":1890,"기권":33878,"candidates":[{"label":"더불어민주당김태룡","votes":11049},{"label":"더불어민주당엄소영","votes":7665},{"label":"국민의힘고락희","votes":6696},{"label":"국민의힘이지원","votes":5248},{"label":"조국혁신당전용길","votes":1033},{"label":"개혁신당이해성","votes":786}]},"충남__6__천안시제7선거구":{"선거인수":0,"투표수":0,"무효":0,"기권":0,"무투표":true,"candidates":[]},"충북__6__천안시사선거구":{"선거인수":0,"투표수":0,"무효":0,"기권":0,"무투표":true,"candidates":[]},"충남__6__천안시제8선거구":{"선거인수":0,"투표수":0,"무효":0,"기권":0,"무투표":true,"candidates":[]},"충북__6__천안시아선거구":{"선거인수":0,"투표수":0,"무효":0,"기권":0,"무투표":true,"candidates":[]},"충남__6__천안시제11선거구":{"선거인수":0,"투표수":0,"무효":0,"기권":0,"무투표":true,"candidates":[]},"충북__6__천안시카선거구":{"선거인수":0,"투표수":0,"무효":0,"기권":0,"무투표":true,"candidates":[]},"충북__6__음성군가선거구":{"선거인수":31504,"투표수":19234,"무효":1197,"기권":12270,"candidates":[{"label":"더불어민주당서효석","votes":6002},{"label":"더불어민주당서형석","votes":2785},{"label":"국민의힘박흥식","votes":4840},{"label":"국민의힘장용식","votes":4102},{"label":"정의당이천규","votes":308}]},"충북__6__음성군나선거구":{"선거인수":29947,"투표수":16946,"무효":864,"기권":13001,"candidates":[{"label":"더불어민주당강영훈","votes":5599},{"label":"더불어민주당송병림","votes":4067},{"label":"국민의힘송춘홍","votes":6416}]},"충북__6__음성군다선거구":{"선거인수":0,"투표수":0,"무효":0,"기권":0,"무투표":true,"candidates":[]},"충북__6__진천군가선거구":{"선거인수":31789,"투표수":18263,"무효":1501,"기권":13526,"candidates":[{"label":"더불어민주당김기복","votes":5816},{"label":"더불어민주당임정구","votes":3520},{"label":"국민의힘윤대영","votes":5967},{"label":"국민의힘홍승의","votes":1459}]},"충북__6__진천군나선거구":{"선거인수":41846,"투표수":23034,"무효":1212,"기권":18812,"candidates":[{"label":"더불어민주당임정열","votes":7414},{"label":"더불어민주당신갑수","votes":3635},{"label":"더불어민주당유후재","votes":4035},{"label":"국민의힘박선진","votes":4567},{"label":"국민의힘이강선","votes":2171}]},"충남__6__천안시라선거구":{"선거인수":0,"투표수":0,"무효":0,"기권":0,"무투표":true,"candidates":[]},"충남__6__천안시마선거구":{"선거인수":0,"투표수":0,"무효":0,"기권":0,"무투표":true,"candidates":[]},"충남__6__천안시바선거구":{"선거인수":0,"투표수":0,"무효":0,"기권":0,"무투표":true,"candidates":[]},"충남__6__천안시사선거구":{"선거인수":0,"투표수":0,"무효":0,"기권":0,"무투표":true,"candidates":[]},"충남__6__천안시아선거구":{"선거인수":0,"투표수":0,"무효":0,"기권":0,"무투표":true,"candidates":[]},"충남__6__천안시카선거구":{"선거인수":0,"투표수":0,"무효":0,"기권":0,"무투표":true,"candidates":[]},"충남__6__천안시가선거구":{"선거인수":0,"투표수":0,"무효":0,"기권":0,"무투표":true,"candidates":[]},"충남__6__천안시나선거구":{"선거인수":0,"투표수":0,"무효":0,"기권":0,"무투표":true,"candidates":[]},"충남__6__천안시다선거구":{"선거인수":60893,"투표수":26663,"무효":1705,"기권":34230,"candidates":[{"label":"더불어민주당복아영","votes":9037},{"label":"더불어민주당정선희","votes":3458},{"label":"국민의힘도병국","votes":7959},{"label":"국민의힘김강진","votes":2871},{"label":"개혁신당손승범","votes":887},{"label":"무소속안종혁","votes":746}]},"충남__6__천안시자선거구":{"선거인수":0,"투표수":0,"무효":0,"기권":0,"무투표":true,"candidates":[]},"충남__6__천안시차선거구":{"선거인수":0,"투표수":0,"무효":0,"기권":0,"무투표":true,"candidates":[]},"충남__6__보령시가선거구":{"선거인수":0,"투표수":0,"무효":0,"기권":0,"무투표":true,"candidates":[]},"충남__6__보령시나선거구":{"선거인수":0,"투표수":0,"무효":0,"기권":0,"무투표":true,"candidates":[]},"충남__6__보령시다선거구":{"선거인수":0,"투표수":0,"무효":0,"기권":0,"무투표":true,"candidates":[]},"충남__6__보령시라선거구":{"선거인수":0,"투표수":0,"무효":0,"기권":0,"무투표":true,"candidates":[]},"충남__6__아산시가선거구":{"선거인수":40162,"투표수":21288,"무효":1087,"기권":18874,"candidates":[{"label":"더불어민주당명노봉","votes":10212},{"label":"국민의힘이기애","votes":7335},{"label":"국민의힘신미진","votes":2654}]},"충남__6__아산시나선거구":{"선거인수":0,"투표수":0,"무효":0,"기권":0,"무투표":true,"candidates":[]},"충남__6__아산시다선거구":{"선거인수":0,"투표수":0,"무효":0,"기권":0,"무투표":true,"candidates":[]},"충남__6__아산시라선거구":{"선거인수":0,"투표수":0,"무효":0,"기권":0,"무투표":true,"candidates":[]},"충남__6__아산시마선거구":{"선거인수":0,"투표수":0,"무효":0,"기권":0,"무투표":true,"candidates":[]},"충북__6__공주시가선거구":{"선거인수":0,"투표수":0,"무효":0,"기권":0,"무투표":true,"candidates":[]},"충남__6__아산시바선거구":{"선거인수":0,"투표수":0,"무효":0,"기권":0,"무투표":true,"candidates":[]},"충북__6__공주시나선거구":{"선거인수":0,"투표수":0,"무효":0,"기권":0,"무투표":true,"candidates":[]},"충북__6__공주시다선거구":{"선거인수":0,"투표수":0,"무효":0,"기권":0,"무투표":true,"candidates":[]},"충남__6__괴산군가선거구":{"선거인수":0,"투표수":0,"무효":0,"기권":0,"무투표":true,"candidates":[]},"충북__6__공주시라선거구":{"선거인수":0,"투표수":0,"무효":0,"기권":0,"무투표":true,"candidates":[]},"충남__6__괴산군나선거구":{"선거인수":0,"투표수":0,"무효":0,"기권":0,"무투표":true,"candidates":[]},"충남__6__괴산군다선거구":{"선거인수":0,"투표수":0,"무효":0,"기권":0,"무투표":true,"candidates":[]},"충남__6__증평군가선거구":{"선거인수":0,"투표수":0,"무효":0,"기권":0,"무투표":true,"candidates":[]},"충남__6__증평군나선거구":{"선거인수":0,"투표수":0,"무효":0,"기권":0,"무투표":true,"candidates":[]},"충남__6__증평군다선거구":{"선거인수":0,"투표수":0,"무효":0,"기권":0,"무투표":true,"candidates":[]},"충남__6__공주시가선거구":{"선거인수":0,"투표수":0,"무효":0,"기권":0,"무투표":true,"candidates":[]},"충남__6__공주시나선거구":{"선거인수":0,"투표수":0,"무효":0,"기권":0,"무투표":true,"candidates":[]},"충남__6__공주시다선거구":{"선거인수":0,"투표수":0,"무효":0,"기권":0,"무투표":true,"candidates":[]},"충남__6__공주시라선거구":{"선거인수":0,"투표수":0,"무효":0,"기권":0,"무투표":true,"candidates":[]},"충남__6__논산시가선거구":{"선거인수":0,"투표수":0,"무효":0,"기권":0,"무투표":true,"candidates":[]},"충남__6__논산시나선거구":{"선거인수":0,"투표수":0,"무효":0,"기권":0,"무투표":true,"candidates":[]},"충남__6__논산시다선거구":{"선거인수":0,"투표수":0,"무효":0,"기권":0,"무투표":true,"candidates":[]},"충남__6__계룡시가선거구":{"선거인수":23388,"투표수":15407,"무효":564,"기권":7981,"candidates":[{"label":"더불어민주당이희정","votes":4327},{"label":"더불어민주당이양희","votes":2940},{"label":"국민의힘이용권","votes":3646},{"label":"국민의힘신동원","votes":1830},{"label":"국민의힘이승진","votes":1756},{"label":"개혁신당손영훈","votes":344}]},"충남__6__계룡시나선거구":{"선거인수":14580,"투표수":9422,"무효":469,"기권":5158,"candidates":[{"label":"더불어민주당황정호","votes":2462},{"label":"더불어민주당이미옥","votes":1412},{"label":"국민의힘강흥식","votes":1883},{"label":"국민의힘김미정","votes":2222},{"label":"조국혁신당최헌묵","votes":462},{"label":"개혁신당한민희","votes":393},{"label":"무소속이정훈","votes":119}]},"충남__6__당진시가선거구":{"선거인수":19210,"투표수":11573,"무효":660,"기권":7637,"candidates":[{"label":"더불어민주당김명진","votes":3836},{"label":"더불어민주당이화용","votes":2544},{"label":"국민의힘김연경","votes":4533}]},"충남__6__당진시나선거구":{"선거인수":23181,"투표수":13592,"무효":599,"기권":9589,"candidates":[{"label":"더불어민주당김초롱","votes":6202},{"label":"국민의힘문선이","votes":2700},{"label":"국민의힘서영훈","votes":4091}]},"충남__6__당진시다선거구":{"선거인수":46634,"투표수":25017,"무효":1404,"기권":21617,"candidates":[{"label":"더불어민주당안요진","votes":7512},{"label":"더불어민주당윤명수","votes":4627},{"label":"국민의힘김덕주","votes":5694},{"label":"국민의힘전영옥","votes":2709},{"label":"조국혁신당조상익","votes":544},{"label":"진보당오윤희","votes":2047},{"label":"무소속한광희","votes":480}]},"충남__6__당진시라선거구":{"선거인수":58851,"투표수":33643,"무효":1723,"기권":25208,"candidates":[{"label":"더불어민주당박명우","votes":8023},{"label":"더불어민주당한상화","votes":3332},{"label":"더불어민주당김선호","votes":4507},{"label":"국민의힘김용균","votes":6121},{"label":"국민의힘김명회","votes":3905},{"label":"개혁신당고재윤","votes":1466},{"label":"진보당김진숙","votes":2778},{"label":"무소속심의수","votes":1788}]},"충남__6__부여군가선거구":{"선거인수":25518,"투표수":18091,"무효":887,"기권":7427,"candidates":[{"label":"더불어민주당서장원","votes":2767},{"label":"더불어민주당노승호","votes":2554},{"label":"더불어민주당유두종","votes":1635},{"label":"더불어민주당김경철","votes":734},{"label":"국민의힘서정호","votes":2607},{"label":"국민의힘박순화","votes":2992},{"label":"국민의힘장소미","votes":2451},{"label":"무소속윤택영","votes":1464}]},"충남__6__부여군나선거구":{"선거인수":14956,"투표수":10489,"무효":595,"기권":4467,"candidates":[{"label":"더불어민주당윤선예","votes":2365},{"label":"더불어민주당구기홍","votes":1428},{"label":"더불어민주당유기주","votes":1105},{"label":"국민의힘이관동","votes":2109},{"label":"국민의힘백용달","votes":1457},{"label":"무소속김기일","votes":1430}]},"충남__6__부여군다선거구":{"선거인수":12928,"투표수":8958,"무효":305,"기권":3970,"candidates":[{"label":"더불어민주당김병철","votes":2431},{"label":"국민의힘조덕연","votes":2565},{"label":"국민의힘조재범","votes":933},{"label":"진보당김지숙","votes":1249},{"label":"무소속김종수","votes":1475}]},"충남__6__서천군가선거구":{"선거인수":20377,"투표수":13530,"무효":1018,"기권":6847,"candidates":[{"label":"더불어민주당조성훈","votes":4290},{"label":"더불어민주당박노찬","votes":2898},{"label":"국민의힘노성철","votes":3626},{"label":"국민의힘김원섭","votes":1698}]},"충남__6__서천군나선거구":{"선거인수":22931,"투표수":16040,"무효":889,"기권":6891,"candidates":[{"label":"더불어민주당김재민","votes":3729},{"label":"더불어민주당이강선","votes":3103},{"label":"국민의힘송혜연","votes":3474},{"label":"국민의힘강신두","votes":3162},{"label":"무소속한경석","votes":1683}]},"충남__6__홍성군가선거구":{"선거인수":29944,"투표수":17780,"무효":1182,"기권":12164,"candidates":[{"label":"더불어민주당송효진","votes":5025},{"label":"더불어민주당최선경","votes":3072},{"label":"국민의힘권영식","votes":5062},{"label":"국민의힘김은미","votes":3439}]},"충남__6__홍성군나선거구":{"선거인수":30088,"투표수":19366,"무효":460,"기권":10722,"candidates":[{"label":"더불어민주당문병오","votes":8454},{"label":"더불어민주당김관태","votes":3266},{"label":"국민의힘김호진","votes":5874},{"label":"조국혁신당조용한","votes":723},{"label":"무소속이호원","votes":589}]},"충남__6__홍성군다선거구":{"선거인수":15180,"투표수":9691,"무효":451,"기권":5489,"candidates":[{"label":"더불어민주당신동규","votes":3802},{"label":"국민의힘신경진","votes":3855},{"label":"국민의힘조현희","votes":1583}]},"충남__6__홍성군라선거구":{"선거인수":12611,"투표수":8157,"무효":383,"기권":4454,"candidates":[{"label":"더불어민주당이정희","votes":2702},{"label":"국민의힘박만","votes":3077},{"label":"국민의힘김덕배","votes":1995}]},"충남__6__청양군가선거구":{"선거인수":19645,"투표수":14567,"무효":730,"기권":5078,"candidates":[{"label":"더불어민주당한대희","votes":3084},{"label":"더불어민주당임상기","votes":2578},{"label":"더불어민주당김미옥","votes":945},{"label":"더불어민주당이경우","votes":1668},{"label":"국민의힘김종대","votes":2045},{"label":"국민의힘이봉규","votes":1833},{"label":"국민의힘정혜선","votes":1684}]},"충남__6__청양군나선거구":{"선거인수":8280,"투표수":6226,"무효":361,"기권":2054,"candidates":[{"label":"더불어민주당김평수","votes":2050},{"label":"더불어민주당최광석","votes":1103},{"label":"국민의힘이장우","votes":1309},{"label":"국민의힘윤일묵","votes":1403}]},"충남__6__예산군가선거구":{"선거인수":25298,"투표수":15514,"무효":783,"기권":9784,"candidates":[{"label":"더불어민주당오현주","votes":3258},{"label":"더불어민주당고진석","votes":2392},{"label":"국민의힘황두현","votes":2672},{"label":"국민의힘이길원","votes":2597},{"label":"국민의힘김태금","votes":2551},{"label":"무소속박성실","votes":1261}]},"충남__6__예산군나선거구":{"선거인수":8209,"투표수":5669,"무효":234,"기권":2540,"candidates":[{"label":"더불어민주당이정호","votes":2000},{"label":"국민의힘박중수","votes":2098},{"label":"국민의힘이상우","votes":1337}]},"충남__6__예산군다선거구":{"선거인수":23001,"투표수":14415,"무효":496,"기권":8586,"candidates":[{"label":"더불어민주당이정순","votes":6402},{"label":"국민의힘장순관","votes":5009},{"label":"국민의힘임종용","votes":2508}]},"충남__6__예산군라선거구":{"선거인수":14538,"투표수":9130,"무효":403,"기권":5408,"candidates":[{"label":"더불어민주당임애민","votes":2509},{"label":"국민의힘김영진","votes":3352},{"label":"국민의힘박종국","votes":1070},{"label":"진보당장동진","votes":1137},{"label":"무소속홍원표","votes":659}]}}